README.md
setup.py
pxp/__init__.py
pxp/ast.py
pxp/compiler.py
pxp/exception.py
pxp/function.py
pxp/interpreter.py
pxp/operator.py
pxp/parser.py
pxp/scope.py
pxp.egg-info/PKG-INFO
pxp.egg-info/SOURCES.txt
pxp.egg-info/dependency_links.txt
pxp.egg-info/requires.txt
pxp.egg-info/top_level.txt
pxp/_interpreter/__init__.py
pxp/_interpreter/resolver.py
pxp/stdlib/__init__.py
pxp/stdlib/general.py
pxp/stdlib/math.py
pxp/stdlib/operator.py
pxp/stdlib/string.py
pxp/stdlib/types.py