Metadata-Version: 1.1
Name: pxp
Version: 0.3.3
Summary: A simple python-hosted expression language.
Home-page: https://github.com/treycucco/pxp
Author: Trey Cucco
Author-email: fcucco@gmail.com
License: MIT
Download-URL: https://github.com/treycucco/pxp/tarball/master
Platform: any
Classifier: Development Status :: 4 - Beta
Classifier: Intended Audience :: Developers
Classifier: License :: OSI Approved :: MIT License
Classifier: Natural Language :: English
Classifier: Operating System :: OS Independent
Classifier: Programming Language :: Python
Classifier: Programming Language :: Python :: 3 :: Only
Classifier: Programming Language :: Python :: 3.4
